snews_cs/Internal Protocols/Coincidence_ALERT_protocol.rst
snews_cs/Internal Protocols/Coincidence_OBS_protocol.rst
snews_cs/__init__.py
snews_cs/__main__.py
snews_cs/_version.py
snews_cs/alert_pub.py
snews_cs/core/__init__.py
snews_cs/core/logging.py
snews_cs/cs_alert_schema.py
snews_cs/cs_email.py
snews_cs/cs_remote_commands.py
snews_cs/cs_stats.py
snews_cs/cs_utils.py
snews_cs/database.py
snews_cs/db_schema.sql
snews_cs/etc/contact_list.json
snews_cs/etc/detector_properties.json
snews_cs/etc/snalert.gif
snews_cs/etc/test-config.env
snews_cs/etc/update_image.png
snews_cs/heartbeat_feedbacks.py
snews_cs/scripts/make_detector_file.py
snews_cs/scripts/server_run.py
snews_cs/snews_bot.py
snews_cs/snews_coinc.py
snews_cs/snews_format_checker.py
snews_cs/snews_hb.py
snews_cs/snews_sql.py
snews_cs/test/test_00_init.py
snews_cs/test/test_01_connection_to_server.py
snews_cs/test/test_02_alert.py
snews_cs/test/test_db.py
snews_cs/test/test_hop.py
snews_cs/test/test_pub_sub.py
snews_cs/test/test_schema.py
snews_cs-3.0.1.dist-info/LICENSE
snews_cs-3.0.1.dist-info/METADATA
snews_cs-3.0.1.dist-info/WHEEL
snews_cs-3.0.1.dist-info/entry_points.txt
snews_cs-3.0.1.dist-info/RECORD
