Metadata-Version: 2.3
Name: snews-cs
Version: 3.0.1
Summary: An alert application for observing supernovas.
License: BSD 3-Clause
Author: SNEWS Collaboration
Author-email: snews2.0@lists.bnl.gov
Requires-Python: >=3.11,<3.13
Classifier: Intended Audience :: Developers
Classifier: Intended Audience :: Science/Research
Classifier: License :: OSI Approved :: BSD License
Classifier: License :: Other/Proprietary License
Classifier: Natural Language :: English
Classifier: Operating System :: MacOS
Classifier: Operating System :: POSIX
Classifier: Operating System :: Unix
Classifier: Programming Language :: Python
Classifier: Programming Language :: Python :: 3
Classifier: Programming Language :: Python :: 3.11
Classifier: Programming Language :: Python :: 3.12
Classifier: Topic :: Scientific/Engineering
Classifier: Topic :: Scientific/Engineering :: Astronomy
Classifier: Topic :: Scientific/Engineering :: Physics
Requires-Dist: click (>=8.1.7,<9.0.0)
Requires-Dist: hop-client (>=0.10.0,<0.11.0)
Requires-Dist: ipython (<7.33.0)
Requires-Dist: matplotlib (>=3.8.0,<4.0.0)
Requires-Dist: numpy (>=1.26.0,<2.0.0)
Requires-Dist: pandas (>=2.1.1,<3.0.0)
Requires-Dist: pymongo (>=4.5.0,<5.0.0)
Requires-Dist: python-dotenv (>=0.19,<0.20)
Requires-Dist: scipy (>=1.11.3,<2.0.0)
Requires-Dist: slack-sdk (>=3.26.2,<4.0.0)
Requires-Dist: snews-data-formats (>=1.0.0,<2.0.0)
Requires-Dist: sqlalchemy (>=2.0.32,<3.0.0)
Requires-Dist: tabulate (>=0.9.0,<0.10.0)
Project-URL: Documentation, https://snews-coincidence-system.readthedocs.io/
Project-URL: Homepage, https://github.com/SNEWS2/SNEWS_Coincidence_System.git
Project-URL: Repository, https://github.com/SNEWS2/SNEWS_Coincidence_System.git
